dbt_diagrams/__init__.py
dbt_diagrams/cli.py
dbt_diagrams/domain.py
dbt_diagrams/input_validators.py
dbt_diagrams/mermaid.py
dbt_diagrams/output_writers.py
dbt_diagrams/resources/mermaid_snippet.html
dbt_diagrams/rest_api.py
dbt_diagrams-0.1.3.dist-info/LICENSE.md
dbt_diagrams-0.1.3.dist-info/METADATA
dbt_diagrams-0.1.3.dist-info/WHEEL
dbt_diagrams-0.1.3.dist-info/entry_points.txt
dbt_diagrams-0.1.3.dist-info/RECORD
