Metadata-Version: 2.1
Name: dbt-diagrams
Version: 0.1.3
Summary: Add Mermaid rendering and model docs based ERDs to your dbt docs
Home-page: https://github.com/DJLemkes/dbt-diagrams
License: MIT
Author: Diederik Jan Lemkes
Author-email: dj.lemkes@gmail.com
Requires-Python: >=3.8,<3.12
Classifier: License :: OSI Approved :: MIT License
Classifier: Programming Language :: Python :: 3
Classifier: Programming Language :: Python :: 3.8
Classifier: Programming Language :: Python :: 3.9
Classifier: Programming Language :: Python :: 3.10
Classifier: Programming Language :: Python :: 3.11
Provides-Extra: all
Provides-Extra: rest-api
Provides-Extra: svg
Requires-Dist: click (==8.1.3)
Requires-Dist: fastapi (==0.105.0) ; extra == "rest-api"
Requires-Dist: playwright (==1.40.0) ; extra == "svg"
Requires-Dist: pydantic (==1.10.13)
Requires-Dist: python-multipart (==0.0.6) ; extra == "rest-api"
Requires-Dist: pyyaml (>=6.0)
Requires-Dist: uvicorn[standard] (==0.24.0) ; extra == "rest-api"
Project-URL: Repository, https://github.com/DJLemkes/dbt-diagrams
